{
  "users": [
    {
      "id": "7508",
      "firstName": "1",
      "lastName": "1",
      "email": "1",
      "phoneNumber": "1",
      "address": "1",
      "password": "1"
    },
    {
      "id": "de94",
      "firstName": "2",
      "lastName": "2",
      "email": "2",
      "phoneNumber": "22",
      "address": "2",
      "password": "2"
    },
    {
      "id": "f7d5",
      "firstName": "3",
      "lastName": "3",
      "email": "33",
      "phoneNumber": "3",
      "address": "3",
      "password": "3"
    }
  ]
}